phaseshifts/__init__.py
phaseshifts/atorb.py
phaseshifts/conphas.py
phaseshifts/elements.py
phaseshifts/leed.py
phaseshifts/model.py
phaseshifts/phsh.py
phaseshifts/settings.py
phaseshifts/.libs/liblibphsh.AF2GOTPAPZEI2N3DSEUHZHX6PRZ7YMUI.gfortran-win_amd64.dll
phaseshifts/contrib/__init__.py
phaseshifts/contrib/xmlrpc_urllib2_transport.py
phaseshifts/gui/ImportDialog.py
phaseshifts/gui/MainWindow.py
phaseshifts/gui/PeriodicTable.py
phaseshifts/gui/SettingsDialog.py
phaseshifts/gui/UpdateDialog.py
phaseshifts/gui/__init__.py
phaseshifts/gui/elements_gui.py
phaseshifts/gui/res_rc.py
phaseshifts/gui/settings.py
phaseshifts/lib/__init__.py
phaseshifts/lib/_fortran_lib.py
phaseshifts/lib/hartfock.py
phaseshifts/lib/libphsh.cp311-win_amd64.pyd
phaseshifts/lib/libphsh.f
phaseshifts/lib/phsh.py
phaseshifts/plugins/__init__.py
phaseshifts/tools/__init__.py
phaseshifts/tools/debye.py
phaseshifts-0.1.8.data/scripts/phsh.py
test/__init__.py
test/test_atorb.py
test/test_imports.py
phaseshifts-0.1.8.dist-info/LICENSE.txt
phaseshifts-0.1.8.dist-info/METADATA
phaseshifts-0.1.8.dist-info/WHEEL
phaseshifts-0.1.8.dist-info/top_level.txt
phaseshifts-0.1.8.dist-info/RECORD
