Metadata-Version: 2.1
Name: phaseshifts
Version: 0.1.8
Summary: Python-based version of the Barbieri/Van Hove phase shift calculation package for LEED/XPD modelling
Home-page: https://github.com/Liam-Deacon/phaseshifts
Author: Liam Deacon
Author-email: liam.m.deacon@gmail.com
License: MIT License
Keywords: phaseshifts atomic scattering muffin-tin diffraction
Platform: UNKNOWN
Classifier: Development Status :: 4 - Beta
Classifier: Environment :: Console
Classifier: Environment :: X11 Applications :: Qt
Classifier: Intended Audience :: Science/Research
Classifier: License :: OSI Approved :: MIT License
Classifier: Operating System :: OS Independent
Classifier: Programming Language :: Python
Classifier: Topic :: Scientific/Engineering :: Chemistry
Classifier: Topic :: Scientific/Engineering :: Physics
Requires-Dist: scipy (>=0.7)
Requires-Dist: numpy (>=1.3)
Requires-Dist: periodictable
Requires-Dist: typing-extensions
Provides-Extra: atorb
Requires-Dist: mendeleev ; extra == 'atorb'
Requires-Dist: elementy ; extra == 'atorb'
Provides-Extra: dev
Requires-Dist: black ; extra == 'dev'
Requires-Dist: isort ; extra == 'dev'
Requires-Dist: numpy ; extra == 'dev'
Requires-Dist: pre-commit ; extra == 'dev'
Requires-Dist: ruff ; extra == 'dev'
Requires-Dist: wheel ; extra == 'dev'
Requires-Dist: scikit-build ; (python_version > "3.11") and extra == 'dev'
Provides-Extra: doc
Requires-Dist: sphinx (<8,>=7) ; extra == 'doc'
Requires-Dist: sphinx-rtd-theme ; extra == 'doc'
Requires-Dist: numpydoc ; extra == 'doc'
Requires-Dist: ipykernel ; extra == 'doc'
Provides-Extra: gui
Provides-Extra: test
Requires-Dist: pytest ; extra == 'test'
Requires-Dist: pytest-cov ; extra == 'test'
